pbatoolkit-0.0.10.dist-info/RECORD
pbatoolkit-0.0.10.dist-info/WHEEL
pbatoolkit-0.0.10.dist-info/METADATA
pbatoolkit-0.0.10.dist-info/licenses/LICENSE
pbatoolkit/_pbat.cpython-310-darwin.so
pbatoolkit/sim.py
pbatoolkit/libPhysicsBasedAnimationToolkit.a
pbatoolkit/libTracyClient.a
pbatoolkit/__init__.py
pbatoolkit/geometry.py
pbatoolkit/gpu.py
pbatoolkit/fem.py
pbatoolkit/profiling.py
pbatoolkit/math/__init__.py
pbatoolkit/math/linalg/__init__.py
